tea_encrypt/__init__.py
tea_encrypt/version.py
tea_encrypt/utils/__init__.py
tea_encrypt/utils/pyctea.py
tea_encrypt/utils/pytea.py
tea_encrypt-0.0.1.dist-info/METADATA
tea_encrypt-0.0.1.dist-info/WHEEL
tea_encrypt-0.0.1.dist-info/top_level.txt
tea_encrypt-0.0.1.dist-info/RECORD
