Metadata-Version: 2.1
Name: tea_encrypt
Version: 0.0.1
Summary: tea_encrypt
Home-page: https://github.com/fiefdx/tea_encrypt
Author: fiefdx
Author-email: fiefdx@163.com
License: MIT
Platform: UNKNOWN
Classifier: License :: OSI Approved :: MIT License
Classifier: Programming Language :: Python :: 3
Classifier: Programming Language :: Python :: 3.7
